azure/mgmt/guestconfig/__init__.py
azure/mgmt/guestconfig/_configuration.py
azure/mgmt/guestconfig/_guest_configuration_client.py
azure/mgmt/guestconfig/_patch.py
azure/mgmt/guestconfig/_serialization.py
azure/mgmt/guestconfig/_vendor.py
azure/mgmt/guestconfig/_version.py
azure/mgmt/guestconfig/py.typed
azure/mgmt/guestconfig/aio/__init__.py
azure/mgmt/guestconfig/aio/_configuration.py
azure/mgmt/guestconfig/aio/_guest_configuration_client.py
azure/mgmt/guestconfig/aio/_patch.py
azure/mgmt/guestconfig/aio/operations/__init__.py
azure/mgmt/guestconfig/aio/operations/_guest_configuration_assignment_reports_operations.py
azure/mgmt/guestconfig/aio/operations/_guest_configuration_assignment_reports_vmss_operations.py
azure/mgmt/guestconfig/aio/operations/_guest_configuration_assignments_operations.py
azure/mgmt/guestconfig/aio/operations/_guest_configuration_assignments_vmss_operations.py
azure/mgmt/guestconfig/aio/operations/_guest_configuration_hcrp_assignment_reports_operations.py
azure/mgmt/guestconfig/aio/operations/_guest_configuration_hcrp_assignments_operations.py
azure/mgmt/guestconfig/aio/operations/_operations.py
azure/mgmt/guestconfig/aio/operations/_patch.py
azure/mgmt/guestconfig/models/__init__.py
azure/mgmt/guestconfig/models/_guest_configuration_client_enums.py
azure/mgmt/guestconfig/models/_models_py3.py
azure/mgmt/guestconfig/models/_patch.py
azure/mgmt/guestconfig/operations/__init__.py
azure/mgmt/guestconfig/operations/_guest_configuration_assignment_reports_operations.py
azure/mgmt/guestconfig/operations/_guest_configuration_assignment_reports_vmss_operations.py
azure/mgmt/guestconfig/operations/_guest_configuration_assignments_operations.py
azure/mgmt/guestconfig/operations/_guest_configuration_assignments_vmss_operations.py
azure/mgmt/guestconfig/operations/_guest_configuration_hcrp_assignment_reports_operations.py
azure/mgmt/guestconfig/operations/_guest_configuration_hcrp_assignments_operations.py
azure_mgmt_guestconfig-1.0.0b2.dist-info/LICENSE
azure_mgmt_guestconfig-1.0.0b2.dist-info/METADATA
azure_mgmt_guestconfig-1.0.0b2.dist-info/WHEEL
azure_mgmt_guestconfig-1.0.0b2.dist-info/top_level.txt
azure_mgmt_guestconfig-1.0.0b2.dist-info/RECORD
